sqlalchemy_boltons/__init__.py
sqlalchemy_boltons/core.py
sqlalchemy_boltons/orm.py
sqlalchemy_boltons/py.typed
sqlalchemy_boltons/reset.py
sqlalchemy_boltons/slow.py
sqlalchemy_boltons/sqlite.py
sqlalchemy_boltons/temporary.py
sqlalchemy_boltons-4.0.1.dist-info/AUTHORS.md
sqlalchemy_boltons-4.0.1.dist-info/LICENSE
sqlalchemy_boltons-4.0.1.dist-info/METADATA
sqlalchemy_boltons-4.0.1.dist-info/WHEEL
sqlalchemy_boltons-4.0.1.dist-info/top_level.txt
sqlalchemy_boltons-4.0.1.dist-info/RECORD
