Metadata-Version: 2.1
Name: sqlalchemy-boltons
Version: 4.0.1
Summary: Utilities that should've been inside SQLAlchemy but aren't
Author-email: Eduard Christian Dumitrescu <eduard.c.dumitrescu@gmail.com>
Maintainer-email: Eduard Christian Dumitrescu <eduard.c.dumitrescu@gmail.com>
License: MIT
Project-URL: Homepage, https://hydra.ecd.space/deaduard/sqlalchemy_boltons/
Project-URL: Changelog, https://hydra.ecd.space/deaduard/sqlalchemy_boltons/file?name=CHANGELOG.md&ci=trunk
Classifier: Programming Language :: Python :: 3
License-File: LICENSE
License-File: AUTHORS.md
Provides-Extra: sqlite
Requires-Dist: immutabledict ; extra == 'sqlite'
